hfst_altlab/__init__.py
hfst_altlab/import_test.py
hfst_altlab/types.py
hfst_altlab-0.1.2.dist-info/licenses/LICENSE
hfst_altlab-0.1.2.dist-info/METADATA
hfst_altlab-0.1.2.dist-info/WHEEL
hfst_altlab-0.1.2.dist-info/top_level.txt
hfst_altlab-0.1.2.dist-info/RECORD
