Metadata-Version: 2.4
Name: hfst-altlab
Version: 0.1.2
Summary: A python wrapper for accessing Helsinki Finite State Transducers used at ALTLab
Author-email: Felipe Bañados Schwerter <banadoss@ualberta.ca>
License-Expression: Apache-2.0
Project-URL: Homepage, https://github.com/UAlbertaALTLab/hfst-altlab
Project-URL: Issues, https://github.com/UAlbertaALTLab/hfst-altlab/issues
Classifier: Topic :: Text Processing :: Linguistic
Classifier: Topic :: Software Development :: Build Tools
Requires-Python: >=3.9
License-File: LICENSE
Requires-Dist: hfst
Dynamic: license-file
